{
  "className": "Commercial",
  "dealership": {
    "dealership": "Vehicle Shop",
    "category": "Premium",
    "price": 200000000,
    "premium": true
  },
  "classId": 20,
  "_data_generated": "2024-01-06 18:17:52",
  "customClass": "Semi-Cabs",
  "seats": 2,
  "model": "w900",
  "hash": 730959932,
  "gameName": "W900",
  "makeName": "JOBUILT",
  "displayName": "Kenworth W900",
  "credits": {
    "author": "Mrjappie241",
    "download": "https://www.gta5-mods.com/vehicles/2014-kenworth-w900-6x2-mid-cab-livery-extras-add-on-replace-mrjappie241"
  },
  "preview": "https://cdn.tycoon.community/dealership/vehicles/w900.png",
  "name": "JoBuilt Kenworth W900",
  "manufacturer": "JoBuilt"
}